gasearch/__init__.py
gasearch/_search.py
gasearch/_selections.py
gasearch/_version.py
gasearch/tests/__init__.py
gasearch/tests/test_common.py
gasearch/tests/test_mutator.py
gasearch-0.0.7.dist-info/LICENSE
gasearch-0.0.7.dist-info/METADATA
gasearch-0.0.7.dist-info/WHEEL
gasearch-0.0.7.dist-info/top_level.txt
gasearch-0.0.7.dist-info/RECORD
